pybaseconfig/__init__.py
pybaseconfig/env_reader.py
PyBaseConfig-0.1.0.dist-info/METADATA
PyBaseConfig-0.1.0.dist-info/WHEEL
PyBaseConfig-0.1.0.dist-info/top_level.txt
PyBaseConfig-0.1.0.dist-info/RECORD
