Metadata-Version: 2.1
Name: PyBaseConfig
Version: 0.1.0
Summary: Ein Python-Paket zur Verwaltung Ihrer Umgebungsvariablen.
License: UNKNOWN
Platform: UNKNOWN
Classifier: License :: OSI Approved :: MIT License
Classifier: Operating System :: OS Independent
Classifier: Programming Language :: Python :: 3.7
Classifier: Programming Language :: Python :: 3.8
Classifier: Programming Language :: Python :: 3.9
Classifier: Programming Language :: Python :: 3.10
Classifier: Programming Language :: Python :: 3.11
